<?xml version="1.0" encoding="UTF-8"?>
<!--
To change this license header, choose License Headers in Project Properties.
To change this template file, choose Tools | Templates
and open the template in the editor.
-->


<userlist>
<userid>usr01</userid>
<username>Sathishkumar</username>
<address>Erode</address>
<phone>9213454567</phone>
<email>sathish@gmail.com</email>
<userid>usr02</userid>
<username>Praveen</username>
<address>Erode</address>
<phone>9994244540</phone>
<email>praveen@gmail.com</email>
<userid>usr03</userid>
<username>sadhik</username>
<address>Erode</address>
<phone>9994244542</phone>
<email>sadhik@gmail.com</email>
<userid>usr04</userid>
<username>ssathish</username>
<address>Dharmapurai</address>
<phone>9835994445</phone>
<email>ssathish@gmail.com</email>
<userid>usr05</userid>
<username>naveen</username>
<address>Perundurai</address>
<phone>968877555</phone>
<email>naveen@gmail.com</email>
</userlist>
